djmongoauth/DjMongoAuthError.py
djmongoauth/__init__.py
djmongoauth/apps.py
djmongoauth/models.py
djmongoauth/common/Email.py
djmongoauth/common/EmailFactory.py
djmongoauth/common/EmailTypes.py
djmongoauth/common/EmailUtils.py
djmongoauth/common/__init__.py
djmongoauth/decorators/__init__.py
djmongoauth/decorators/authenticated.py
djmongoauth/migrations/__init__.py
djmongoauth-0.0.1.dist-info/METADATA
djmongoauth-0.0.1.dist-info/WHEEL
djmongoauth-0.0.1.dist-info/top_level.txt
djmongoauth-0.0.1.dist-info/RECORD
