Metadata-Version: 2.1
Name: djmongoauth
Version: 0.0.1
Summary: Out-of-the-box support register, sign in, email verification and password recovery workflows for websites based on Django and MongoDB
Home-page: https://github.com/Haotian9850/djmongoauth
Author: hao
Author-email: hl7gr@virginia.edu
License: MIT
Platform: UNKNOWN
Classifier: Framework :: Django
Classifier: Programming Language :: Python :: 3
Requires-Dist: djongo (==1.3.1)
Requires-Dist: Django (>=2.2.24)
